{
    "table_id": "wikisql_018da58bf9",
    "source": "wikisql",
    "original_metadata": {
        "source_dataset": "wikisql",
        "table_page_title": "Comparison of brainwave entrainment software"
    },
    "dimensions": {
        "rows": 9,
        "columns": 5
    },
    "schema": {
        "columns": [
            "Software",
            "Version",
            "Operating systems",
            "Developer",
            "License"
        ],
        "dtypes": {
            "Software": "object",
            "Version": "object",
            "Operating systems": "object",
            "Developer": "object",
            "License": "object"
        }
    }
}