{
    "table_id": "wikisql_864f96c7c5",
    "source": "wikisql",
    "original_metadata": {
        "source_dataset": "wikisql",
        "table_page_title": "Italy"
    },
    "dimensions": {
        "rows": 19,
        "columns": 5
    },
    "schema": {
        "columns": [
            "Region",
            "Capital",
            "Area (km\u00b2)",
            "Area (sq mi)",
            "Population"
        ],
        "dtypes": {
            "Region": "object",
            "Capital": "object",
            "Area (km\u00b2)": "object",
            "Area (sq mi)": "object",
            "Population": "object"
        }
    }
}