[
  {
    "question_id": "wikisql_994c53559b_001",
    "table_id": "wikisql_994c53559b",
    "question_type": "open_ended_reasoning",
    "question": "Ono ora hubungane antarane ngamanake posisi pole lan menangake balapan GT3? Wenehana analisis adhedhasar data.",
    "answer": [
      [
        "Ana hubungane sing ringkih antarane ngamanake posisi pole lan menangake balapan GT3. Saka 14 babak, tim sing wiwit saka posisi pole sukses menangake balapan GT3 mung ing 3 kasus: 'No. 1 Barwell Motorsport' ing Babak 5, 'No. 6 Team RPM' ing Babak 6, lan 'No. 23 Christians in Motorsport' ing Babak 12. Iki nuduhake tingkat kamenangan kira-kira 21,4% saka pole, nuduhake yen posisi pole menehi keuntungan sing sithik utawa ora ana sing signifikan kanggo ngamanake kamenangan kelas GT3 ing musim kejuaraan iki."
      ]
    ],
    "evidence_cells": [
      "E1",
      "F1",
      "E3",
      "F3",
      "E5",
      "F5",
      "E7",
      "F7",
      "E9",
      "F9",
      "E11",
      "F11",
      "E13",
      "F13",
      "E15",
      "F15",
      "E17",
      "F17",
      "E19",
      "F19",
      "E21",
      "F21",
      "E23",
      "F23",
      "E25",
      "F25",
      "E27",
      "F27"
    ],
    "reasoning_category": "Correlation Inference"
  },
  {
    "question_id": "wikisql_994c53559b_002",
    "table_id": "wikisql_994c53559b",
    "question_type": "value",
    "question": "Pasangan pembalap endi sing menang kelas GTC ing balapan paling dawa musim iki?",
    "answer": [
      [
        "Keith Ahlers Steve Hyde"
      ],
      [
        "Graeme Mundy Jamie Smyth"
      ]
    ],
    "evidence_cells": [
      "D9",
      "G10",
      "D15",
      "G16"
    ],
    "reasoning_category": "Multi-Hop Reasoning"
  },
  {
    "question_id": "wikisql_994c53559b_003",
    "table_id": "wikisql_994c53559b",
    "question_type": "value",
    "question": "Piro total durasi balap gabungan ing menit kanggo kabeh babak sing dianakake ing Donington Park lan Brands Hatch?",
    "answer": [
      [
        "240"
      ]
    ],
    "evidence_cells": [
      "B5",
      "D5",
      "B7",
      "D7",
      "B11",
      "D11",
      "B13",
      "D13"
    ],
    "reasoning_category": "Numerical Aggregation"
  },
  {
    "question_id": "wikisql_994c53559b_004",
    "table_id": "wikisql_994c53559b",
    "question_type": "value",
    "question": "Sebutna tim GT3 sing menang ing balapan sing ora dianakake ing April utawa September.",
    "answer": [
      [
        "No. 1 Barwell Motorsport"
      ],
      [
        "No. 6 Team RPM"
      ],
      [
        "No. 23 Christians in Motorsport"
      ],
      [
        "No. 3 Barwell Motorsport"
      ]
    ],
    "evidence_cells": [
      "C9",
      "F9",
      "C11",
      "F11",
      "C13",
      "F13",
      "C15",
      "F15",
      "C17",
      "F17",
      "C19",
      "F19"
    ],
    "reasoning_category": "Conditional Reasoning"
  },
  {
    "question_id": "wikisql_994c53559b_005",
    "table_id": "wikisql_994c53559b",
    "question_type": "value",
    "question": "Tim balap endi sing padha-padha paling akèh menang nalika nggabungaké kamenangan kelas GT3 lan GTC?",
    "answer": [
      [
        "Barwell Motorsport"
      ],
      [
        "Beechdean Motorsport"
      ]
    ],
    "evidence_cells": [
      "F5",
      "F7",
      "F9",
      "F17",
      "F19",
      "G5",
      "G7",
      "G19",
      "G25",
      "G27"
    ],
    "reasoning_category": "Comparative Reasoning"
  },
  {
    "question_id": "wikisql_994c53559b_006",
    "table_id": "wikisql_994c53559b",
    "question_type": "open_ended_reasoning",
    "question": "Analisa tren performa tim 'No. 99 Beechdean Motorsport' ing kelas GTC sakabehing mangsa.",
    "answer": [
      [
        "Performa tim 'No. 99 Beechdean Motorsport' ditandai kanthi wiwitan sing kuwat lan pungkasane luwih kuat, kanthi kesenjangan kompetitif sing suwe ing tengah mangsa. Tim kasebut menang kaping pindho ing Donington Park ing wulan April (Ronde 3 & 4), banjur ora menang maneh nganti pungkasane Agustus ing Thruxton (Ronde 10). Tim kasebut mungkasi mangsa kanthi dominan kanthi rong kamenangan liyane ing Rockingham ing pungkasane September (Ronde 13 & 14), dadi salah sawijining tim GTC sing paling sukses nanging kanthi performa sing ora konsisten sakabehing mangsa."
      ]
    ],
    "evidence_cells": [
      "A5",
      "C5",
      "G5",
      "A7",
      "C7",
      "G7",
      "A19",
      "C19",
      "G19",
      "A25",
      "C25",
      "G25",
      "A27",
      "C27",
      "G27"
    ],
    "reasoning_category": "Temporal Reasoning"
  },
  {
    "question_id": "wikisql_994c53559b_007",
    "table_id": "wikisql_994c53559b",
    "question_type": "value",
    "question": "Pira persentase kabeh kamenangan kelas GT3 sing dikuwasani dening tim saka 'Barwell Motorsport' (kalebu entri No. 1, No. 2, lan No. 3)?",
    "answer": [
      [
        "35.71"
      ]
    ],
    "evidence_cells": [
      "F5",
      "F7",
      "F9",
      "F17",
      "F19",
      "A1",
      "A3",
      "A5",
      "A7",
      "A9",
      "A11",
      "A13",
      "A15",
      "A17",
      "A19",
      "A21",
      "A23",
      "A25",
      "A27"
    ],
    "reasoning_category": "Proportional/Ratio Analysis"
  },
  {
    "question_id": "wikisql_994c53559b_008",
    "table_id": "wikisql_994c53559b",
    "question_type": "value",
    "question": "Sirkuit endi wae sing nduwe durasi balapan sing beda tinimbang liyane ing musim iki?",
    "answer": [
      [
        "Snetterton"
      ],
      [
        "Silverstone"
      ]
    ],
    "evidence_cells": [
      "B9",
      "D9",
      "B15",
      "D15",
      "D1",
      "D3",
      "D5",
      "D7",
      "D11",
      "D13",
      "D17",
      "D19",
      "D21",
      "D23",
      "D25",
      "D27"
    ],
    "reasoning_category": "Outlier Detection"
  },
  {
    "question_id": "wikisql_994c53559b_009",
    "table_id": "wikisql_994c53559b",
    "question_type": "value",
    "question": "Nek balapan 120 menit sing ping loro mau dadi balapan sprint 60 menit sing lumrah, kira-kira total wektu balapan sak mangsa iki dadi pira jam?",
    "answer": [
      [
        "14"
      ]
    ],
    "evidence_cells": [
      "D1",
      "D3",
      "D5",
      "D7",
      "D9",
      "D11",
      "D13",
      "D15",
      "D17",
      "D19",
      "D21",
      "D23",
      "D25",
      "D27"
    ],
    "reasoning_category": "Hypothetical Reasoning"
  },
  {
    "question_id": "wikisql_994c53559b_010",
    "table_id": "wikisql_994c53559b",
    "question_type": "open_ended_reasoning",
    "question": "Ndelok struktur tabele, opo bedane umum ing data baris ganjil dibanding karo baris genep kanggo kolom E, F, lan G?",
    "answer": [
      [
        "Tabel iki disususn nganggo pola sing konsisten kanggo kolom 'Pole Position', 'GT3 Winner', lan 'GTC Winner'. Baris ganjil (1, 3, 5, lsp.) mesthi ngandhut jeneng tim resmi, sing biasane nyakup nomer mobil. Baris genep sabanjure (2, 4, 6, lsp.) menehi jeneng lengkap pembalap utawa pasangan pembalap sing cocog kanggo entri kasebut."
      ]
    ],
    "evidence_cells": [
      "E1",
      "E2",
      "F1",
      "F2",
      "G1",
      "G2",
      "E3",
      "E4",
      "F3",
      "F4",
      "G3",
      "G4"
    ],
    "reasoning_category": "Structural/Metadata Reasoning"
  },
  {
    "question_id": "wikisql_994c53559b_011",
    "table_id": "wikisql_994c53559b",
    "question_type": "open_ended_reasoning",
    "question": "Ring-ring endi sing suwene luwih saka 60 menit?",
    "answer": [
      [
        "Ring 5 lan 8 suwene 120 menit saben-saben."
      ]
    ],
    "evidence_cells": [
      "D9",
      "D10",
      "D15",
      "D16"
    ],
    "reasoning_category": "Outlier Detection"
  }
]