[
  {
    "question_id": "wikisql_592ca23134_001",
    "table_id": "wikisql_592ca23134",
    "question_type": "value",
    "question": "Cale condado at bidìt sa pprintzale differenza de puntu intre Kerry e Bush?",
    "answer": [
      [
        "Winnebago"
      ]
    ],
    "evidence_cells": [
      "A6",
      "B6",
      "D6"
    ],
    "reasoning_category": "Comparative Reasoning"
  },
  {
    "question_id": "wikisql_592ca23134_002",
    "table_id": "wikisql_592ca23134",
    "question_type": "value",
    "question": "Cales fiat su númuru totu de votos pro Bohe a traessu de totu sos contados listados?",
    "answer": [
      [
        "534400"
      ]
    ],
    "evidence_cells": [
      "E1",
      "E2",
      "E3",
      "E4",
      "E5",
      "E6",
      "E7",
      "E8",
      "E9",
      "E10",
      "E11",
      "E12",
      "E13",
      "E14",
      "E15",
      "E16",
      "E17",
      "E18",
      "E19",
      "E20",
      "E21",
      "E22"
    ],
    "reasoning_category": "Numerical Aggregation"
  },
  {
    "question_id": "wikisql_592ca23134_003",
    "table_id": "wikisql_592ca23134",
    "question_type": "value",
    "question": "In bidda cun su nìmberu prus bassu de totu sos votos (Kerry# + Bush# + Others#), cale fiat sa fetta de su votu de Kerry?",
    "answer": [
      [
        "50.8%"
      ]
    ],
    "evidence_cells": [
      "A22",
      "C22",
      "E22",
      "G22",
      "B22"
    ],
    "reasoning_category": "Multi-Hop Reasoning"
  },
  {
    "question_id": "wikisql_592ca23134_004",
    "table_id": "wikisql_592ca23134",
    "question_type": "value",
    "question": "Cunnosce in totus is comtados ue Bush at otènnidu prus de su 60% de is votos E Kerry at otènnidu pagu de 5.000 votos.",
    "answer": [
      [
        "Cumberland"
      ],
      [
        "Johnson"
      ],
      [
        "Ford"
      ],
      [
        "Effingham"
      ]
    ],
    "evidence_cells": [
      "A3",
      "D3",
      "C3",
      "A8",
      "D8",
      "C8",
      "A9",
      "D9",
      "C9",
      "A12",
      "D12",
      "C12",
      "A15",
      "D15",
      "C15",
      "A16",
      "D16",
      "C16",
      "A17",
      "D17",
      "C17"
    ],
    "reasoning_category": "Conditional Reasoning"
  },
  {
    "question_id": "wikisql_592ca23134_005",
    "table_id": "wikisql_592ca23134",
    "question_type": "value",
    "question": "Cal'est sa parte de sos votos de Kerry de totus sos comitados listados chi est benìda dae su comitadu unicu in ue at tentu prus votos?",
    "answer": [
      [
        "41.2%"
      ]
    ],
    "evidence_cells": [
      "C1",
      "C2",
      "C3",
      "C4",
      "C5",
      "C6",
      "C7",
      "C8",
      "C9",
      "C10",
      "C11",
      "C12",
      "C13",
      "C14",
      "C15",
      "C16",
      "C17",
      "C18",
      "C19",
      "C20",
      "C21",
      "C22"
    ],
    "reasoning_category": "Proportional/Ratio Analysis"
  },
  {
    "question_id": "wikisql_592ca23134_006",
    "table_id": "wikisql_592ca23134",
    "question_type": "open_ended_reasoning",
    "question": "Si sos sos votos pro 'Others' in sa contea de Winnebago fiant torrados a Kerry, diat cambiare su bincidore de cussa contea?",
    "answer": [
      [
        "Eja, su bincidore diat cambiare dae Bush a Kerry. In antis, Bush binciat pro 1.042 votos (60.782 contra 59.740). Torrende a Kerry sos 903 votos de 'Others', diat otènnere 60.643 votos, chi sunt ancora pagos a pustis de su nùmeru de Bush. Pro custu motivu, Bush diat bìnchere ancora, ma cun una diferèntzia de 139 votos prus pagu. Aspeta, devimos torrare a contare. Su puntu de Kerry diat esser 59.740 + 903 = 60.643. Su puntu de Bush est 60.782. Bush ancora bincet. Sa prima cunclusioni mea fiat errada. Su bincidore NO diat cambiare."
      ],
      [
        "No, su bincidore non diat cambiare. Bush in antis binciat cun 60.782 votos contra sos 59.740 de Kerry. Apondende sos 903 votos de 'Others' a su puntu de Kerry, resurtat 60.643 votos, chi sunt ancora pagos a pustis de su puntu de Bush. Bush diat abarrare su bincidore, siat puru cun una diferèntzia de 139 votos prus pagu."
      ]
    ],
    "evidence_cells": [
      "A6",
      "C6",
      "E6",
      "G6"
    ],
    "reasoning_category": "Hypothetical Reasoning"
  },
  {
    "question_id": "wikisql_592ca23134_007",
    "table_id": "wikisql_592ca23134",
    "question_type": "open_ended_reasoning",
    "question": "Basende in datos, b'at una relatzione osservàbiles intre una pertzentuale prus artzada de votos pro 'Others' e una cursa prus agguantada intre Kerry e Bush?",
    "answer": [
      [
        "Non b'at relatzione costante. Su cuntradu cun sa pertzentuale prus artzada de 'Others' est Jackson (1.3%), in ue sa cursa no fiat particularmente agguantada (un'ispartzida de 12.1 puntos pro Kerry). In manera cuntraria, sa cursa prus agguantada fiat in Winnebago (un'ispartzida de 0.9 puntos), chi aiat una pertzentuale de 'Others' suta sa media de 0.7%. Custu suggerit chi sa performàntzia de sos candidados de sa tertzess partìda no est unu preditore affidàbiles de s'ispartzida intre sos duos candidatos printzipales in custu dataset."
      ]
    ],
    "evidence_cells": [
      "B6",
      "D6",
      "F6",
      "B13",
      "D13",
      "F13"
    ],
    "reasoning_category": "Correlation Inference"
  },
  {
    "question_id": "wikisql_592ca23134_008",
    "table_id": "wikisql_592ca23134",
    "question_type": "value",
    "question": "Quale contea est s'isulamentu prus mannu in termos de votos crudos totarmente postos pro totu sos candidadores cumbinados?",
    "answer": [
      [
        "DuPage"
      ]
    ],
    "evidence_cells": [
      "A19",
      "C19",
      "E19",
      "G19"
    ],
    "reasoning_category": "Outlier Detection"
  },
  {
    "question_id": "wikisql_592ca23134_009",
    "table_id": "wikisql_592ca23134",
    "question_type": "value",
    "question": "Cal'est su nùmeru totale de is votos hipotetitzadu in sa contea de Effingham, a pustis de is pertzentuales e contos de votos crudos pro un'únigu candidadu?",
    "answer": [
      [
        "16278"
      ]
    ],
    "evidence_cells": [
      "B16",
      "C16",
      "D16",
      "E16"
    ],
    "reasoning_category": "Multi-Hop Reasoning"
  },
  {
    "question_id": "wikisql_592ca23134_010",
    "table_id": "wikisql_592ca23134",
    "question_type": "value",
    "question": "Chie candidadu, Kerry o Bush, at otentu prus cuntreas in totali, e cun cantu?",
    "answer": [
      [
        "Bush"
      ],
      [
        "10"
      ]
    ],
    "evidence_cells": [
      "B1",
      "D1",
      "B2",
      "D2",
      "B3",
      "D3",
      "B4",
      "D4",
      "B5",
      "D5",
      "B6",
      "D6",
      "B7",
      "D7",
      "B8",
      "D8",
      "B9",
      "D9",
      "B10",
      "D10",
      "B11",
      "D11",
      "B12",
      "D12",
      "B13",
      "D13",
      "B14",
      "D14",
      "B15",
      "D15",
      "B16",
      "D16",
      "B17",
      "D17",
      "B18",
      "D18",
      "B19",
      "D19",
      "B20",
      "D20",
      "B21",
      "D21",
      "B22",
      "D22"
    ],
    "reasoning_category": "Comparative Reasoning"
  },
  {
    "question_id": "wikisql_592ca23134_011",
    "table_id": "wikisql_592ca23134",
    "question_type": "open_ended_reasoning",
    "question": "Quale schema osservas tra sa% de Kerry e sa% de Bush in sa majoria de sos cussorgios?",
    "answer": [
      [
        "In sa majoria de sos cussorgios, sa% de unu candidadu est in relatzione inversamente proporntzionale a s'àteru, montrende una cumpetitzione clàssica de duos partìos cun minores votos pro sos àteros."
      ]
    ],
    "evidence_cells": [
      "B1",
      "D1",
      "B90",
      "D90"
    ],
    "reasoning_category": "Correlation Inference"
  }
]