{
    "table_id": "wikisql_064a672ce1",
    "source": "wikisql",
    "original_metadata": {
        "source_dataset": "wikisql",
        "table_page_title": "2008 V8 Supercar Championship Series"
    },
    "dimensions": {
        "rows": 13,
        "columns": 8
    },
    "schema": {
        "columns": [
            "Rd.",
            "Race Title",
            "Circuit",
            "City / State",
            "Date",
            "Winner",
            "Team",
            "Report"
        ],
        "dtypes": {
            "Rd.": "object",
            "Race Title": "object",
            "Circuit": "object",
            "City / State": "object",
            "Date": "object",
            "Winner": "object",
            "Team": "object",
            "Report": "object"
        }
    }
}