[
  {
    "question_id": "wikisql_a3cfad8be5_001",
    "table_id": "wikisql_a3cfad8be5",
    "question_type": "value",
    "question": "أي مندوب لديه أطول فترة خدمة بناءً على عام \"أول انتخاب\" له، مما يجعله استثنائياً مقارنة بالآخرين؟",
    "answer": [
      [
        "Kach, Wade Wade Kach"
      ]
    ],
    "evidence_cells": [
      "C1",
      "E1",
      "E2",
      "E3",
      "E4",
      "E5",
      "E6",
      "E7",
      "E8",
      "E9",
      "E10",
      "E11",
      "E12",
      "E13",
      "E14",
      "E15",
      "E16",
      "E17",
      "E18",
      "E19"
    ],
    "reasoning_category": "Outlier Detection"
  },
  {
    "question_id": "wikisql_a3cfad8be5_002",
    "table_id": "wikisql_a3cfad8be5",
    "question_type": "value",
    "question": "ما هو العدد الإجمالي للمندوبين الذين تم انتخابهم لأول مرة في عام 2002؟",
    "answer": [
      [
        "9"
      ]
    ],
    "evidence_cells": [
      "E3",
      "E4",
      "E5",
      "E8",
      "E9",
      "E13",
      "E15",
      "E16",
      "E19"
    ],
    "reasoning_category": "Numerical Aggregation"
  },
  {
    "question_id": "wikisql_a3cfad8be5_003",
    "table_id": "wikisql_a3cfad8be5",
    "question_type": "value",
    "question": "ما هو الحزب السياسي الذي يمثله المندوب بأقدم سنة انتخاب؟",
    "answer": [
      [
        "Republican"
      ]
    ],
    "evidence_cells": [
      "D1",
      "E1"
    ],
    "reasoning_category": "Multi-Hop Reasoning"
  },
  {
    "question_id": "wikisql_a3cfad8be5_004",
    "table_id": "wikisql_a3cfad8be5",
    "question_type": "value",
    "question": "اذكر جميع المندوبين الديمقراطيين الذين يخدمون في لجنتي 'المخصصات' أو 'الشؤون البيئية'.",
    "answer": [
      [
        "Weir, Michael H. Jr. Michael H. Weir, Jr."
      ],
      [
        "Jones, Adrienne A. Adrienne A. Jones"
      ],
      [
        "Stein, Dana Dana Stein"
      ],
      [
        "DeBoy, Steven J. Sr. Steven J. DeBoy, Sr."
      ],
      [
        "Lafferty, Stephen W. Stephen W. Lafferty"
      ]
    ],
    "evidence_cells": [
      "C3",
      "D3",
      "F3",
      "C11",
      "D11",
      "F11",
      "C15",
      "D15",
      "F15",
      "C16",
      "D16",
      "F16",
      "C18",
      "D18",
      "F18"
    ],
    "reasoning_category": "Conditional Reasoning"
  },
  {
    "question_id": "wikisql_a3cfad8be5_005",
    "table_id": "wikisql_a3cfad8be5",
    "question_type": "value",
    "question": "ما هي النسبة المئوية للمندوبين المدرجين في الجدول والمنتمين إلى الحزب الديمقراطي؟",
    "answer": [
      [
        "63.16%"
      ]
    ],
    "evidence_cells": [
      "D1",
      "D2",
      "D3",
      "D4",
      "D5",
      "D6",
      "D7",
      "D8",
      "D9",
      "D10",
      "D11",
      "D12",
      "D13",
      "D14",
      "D15",
      "D16",
      "D17",
      "D18",
      "D19"
    ],
    "reasoning_category": "Proportional/Ratio Analysis"
  },
  {
    "question_id": "wikisql_a3cfad8be5_006",
    "table_id": "wikisql_a3cfad8be5",
    "question_type": "value",
    "question": "إذا نصت قاعدة جديدة على أن أي مندوب يمثل أكثر من مقاطعة واحدة يجب أن يخدم في لجنة \"المخصصات\"، فما هي أسماء المندوبين الذين سيحتاجون إلى تغيير مهمتهم في اللجنة؟",
    "answer": [
      [
        "Kach, Wade Wade Kach"
      ],
      [
        "Impallaria, Richard K. Richard K. Impallaria"
      ],
      [
        "Jennings, J. B. J. B. Jennings"
      ],
      [
        "McDonough, Patrick L. Patrick L. McDonough"
      ],
      [
        "Malone, James E. Jr. James E. Malone, Jr."
      ]
    ],
    "evidence_cells": [
      "B1",
      "C1",
      "F1",
      "B4",
      "C4",
      "F4",
      "B5",
      "C5",
      "F5",
      "B6",
      "C6",
      "F6",
      "B16",
      "C16",
      "F16",
      "B17",
      "C17",
      "F17"
    ],
    "reasoning_category": "Hypothetical Reasoning"
  },
  {
    "question_id": "wikisql_a3cfad8be5_007",
    "table_id": "wikisql_a3cfad8be5",
    "question_type": "value",
    "question": "أي لجنة لديها أكبر عدد من الأعضاء من القائمة المقدمة للمندوبين؟",
    "answer": [
      [
        "Health and Government Operations"
      ]
    ],
    "evidence_cells": [
      "F1",
      "F2",
      "F3",
      "F4",
      "F5",
      "F6",
      "F7",
      "F8",
      "F9",
      "F10",
      "F11",
      "F12",
      "F13",
      "F14",
      "F15",
      "F16",
      "F17",
      "F18",
      "F19"
    ],
    "reasoning_category": "Structural/Metadata Reasoning"
  },
  {
    "question_id": "wikisql_a3cfad8be5_008",
    "table_id": "wikisql_a3cfad8be5",
    "question_type": "open_ended_reasoning",
    "question": "بالمقارنة بين المندوبين الذين تم انتخابهم لأول مرة قبل عام 1990 وأولئك الذين تم انتخابهم في عام 2002، أي مجموعة لديها نسبة أعلى من الجمهوريين؟",
    "answer": [
      [
        "المجموعة التي تم انتخابها في عام 2002 لديها نسبة أعلى من الجمهوريين. من بين المندوبين الثلاثة الذين تم انتخابهم قبل عام 1990 (كاتش، مينيك، ماكدونو)، اثنان جمهوريان (66.7%). من بين المندوبين التسعة الذين تم انتخابهم في عام 2002، خمسة جمهوريون (55.6%). لذلك، فإن مجموعة ما قبل عام 1990 لديها نسبة أعلى."
      ]
    ],
    "evidence_cells": [
      "C1",
      "D1",
      "E1",
      "C2",
      "D2",
      "E2",
      "C6",
      "D6",
      "E6",
      "D3",
      "E3",
      "D4",
      "E4",
      "D5",
      "E5",
      "D8",
      "E8",
      "D9",
      "E9",
      "D13",
      "E13",
      "D15",
      "E15",
      "D16",
      "E16",
      "D19",
      "E19"
    ],
    "reasoning_category": "Comparative Reasoning"
  },
  {
    "question_id": "wikisql_a3cfad8be5_009",
    "table_id": "wikisql_a3cfad8be5",
    "question_type": "open_ended_reasoning",
    "question": "هل تشير البيانات إلى وجود ارتباط بين منطقة تمثل مقاطعات متعددة والانتماء الحزبي لمندوبيها؟",
    "answer": [
      [
        "نعم، تشير البيانات إلى وجود ارتباط محتمل. هناك ثلاث مناطق تمثل مقاطعات متعددة: 05.2 5B، 07.0 7، و 12.1 12A. من بين المندوبين الستة من هذه المناطق، أربعة جمهوريون واثنان ديمقراطيون. في المقابل، للمناطق التي تمثل مقاطعة بالتيمور وحدها، عشرة من ثلاثة عشر مندوبًا هم ديمقراطيون. هذا يشير إلى أنه في مجموعة البيانات هذه، من المرجح أن يمثل الجمهوريون المناطق متعددة المقاطعات."
      ]
    ],
    "evidence_cells": [
      "B1",
      "D1",
      "B2",
      "D2",
      "B3",
      "D3",
      "B4",
      "D4",
      "B5",
      "D5",
      "B6",
      "D6",
      "B7",
      "D7",
      "B8",
      "D8",
      "B9",
      "D9",
      "B10",
      "D10",
      "B11",
      "D11",
      "B12",
      "D12",
      "B13",
      "D13",
      "B14",
      "D14",
      "B15",
      "D15",
      "B16",
      "D16",
      "B17",
      "D17",
      "B18",
      "D18",
      "B19",
      "D19"
    ],
    "reasoning_category": "Correlation Inference"
  },
  {
    "question_id": "wikisql_a3cfad8be5_010",
    "table_id": "wikisql_a3cfad8be5",
    "question_type": "open_ended_reasoning",
    "question": "حلل التغيير في التمثيل الحزبي بين المندوبين المنتخبين حديثًا على مر السنين المشمولة في هذا الجدول (1974-2006). هل هناك اتجاه واضح؟",
    "answer": [
      [
        "بناءً على سنوات 'أول انتخاب'، لا يوجد اتجاه واضح ومتسق، بل هناك تقلبات. في السبعينيات والثمانينيات، كان التمثيل مختلطًا (2 جمهوري، 1 ديمقراطي). شهدت التسعينيات طفرة ديمقراطية حيث كان 4 من أصل 5 مندوبين منتخبين حديثًا ديمقراطيين. أكبر مجموعة منفردة، من عام 2002، تظهر حضورًا جمهوريًا قويًا بـ 5 جمهوريين و 4 ديمقراطيين. أحدث عام، 2006، يظهر فقط انتخاب ديمقراطيين. بشكل عام، الاتجاه ليس خطيًا؛ بل يتحول من مختلط، إلى ديمقراطي مكثف، ثم إلى أكثر توازنًا، ويعود إلى الديمقراطي."
      ]
    ],
    "evidence_cells": [
      "D1",
      "E1",
      "D2",
      "E2",
      "D3",
      "E3",
      "D4",
      "E4",
      "D5",
      "E5",
      "D6",
      "E6",
      "D7",
      "E7",
      "D8",
      "E8",
      "D9",
      "E9",
      "D10",
      "E10",
      "D11",
      "E11",
      "D12",
      "E12",
      "D13",
      "E13",
      "D14",
      "E14",
      "D15",
      "E15",
      "D16",
      "E16",
      "D17",
      "E17",
      "D18",
      "E18",
      "D19",
      "E19"
    ],
    "reasoning_category": "Temporal Reasoning"
  },
  {
    "question_id": "wikisql_a3cfad8be5_011",
    "table_id": "wikisql_a3cfad8be5",
    "question_type": "value",
    "question": "ما هي المناطق التي تضم مندوبين جمهوريين وديمقراطيين؟",
    "answer": [
      [
        "08.0 8"
      ],
      [
        "42"
      ]
    ],
    "evidence_cells": [
      "A7",
      "A8",
      "A9",
      "A18",
      "A19",
      "D7",
      "D8",
      "D9",
      "D18",
      "D19"
    ],
    "reasoning_category": "Comparative Reasoning"
  }
]