[
  {
    "question_id": "wikisql_c8bc677481_001",
    "table_id": "wikisql_c8bc677481",
    "question_type": "open_ended_reasoning",
    "question": "दूसरे डिवीज़न में टीम के सर्वश्रेष्ठ प्लेऑफ़ प्रदर्शन की तुलना चौथे डिवीज़न में उनके सर्वश्रेष्ठ प्लेऑफ़ प्रदर्शन से कैसे की जाती है?",
    "answer": [
      [
        "टीम का सर्वश्रेष्ठ प्लेऑफ़ प्रदर्शन चौथे डिवीज़न में काफ़ी बेहतर था, जहाँ वे कई मौकों (2003, 2005, 2006) पर 'नेशनल सेमीफाइनल्स' तक पहुँचे थे। इसके विपरीत, दूसरे डिवीज़न में उनका सर्वश्रेष्ठ प्रदर्शन 1999 में 'कॉन्फ़्रेंस क्वार्टरफाइनल्स' तक पहुँचना था।"
      ]
    ],
    "evidence_cells": [
      "B1",
      "B2",
      "B3",
      "B4",
      "E1",
      "E2",
      "E3",
      "E4",
      "B5",
      "B7",
      "B9",
      "B10",
      "E5",
      "E7",
      "E9",
      "E10"
    ],
    "reasoning_category": "Comparative Reasoning"
  },
  {
    "question_id": "wikisql_c8bc677481_002",
    "table_id": "wikisql_c8bc677481",
    "question_type": "value",
    "question": "ऐसे कितने सीज़न थे जिनमें टीम ने डिवीज़न 4 में खेलते हुए प्लेऑफ़ के लिए क्वालीफाई नहीं किया?",
    "answer": [
      [
        "6"
      ]
    ],
    "evidence_cells": [
      "B5",
      "E5",
      "B6",
      "E6",
      "B7",
      "E7",
      "B8",
      "E8",
      "B9",
      "E9",
      "B10",
      "E10",
      "B11",
      "E11",
      "B12",
      "E12",
      "B13",
      "E13",
      "B14",
      "E14",
      "B15",
      "E15"
    ],
    "reasoning_category": "Numerical Aggregation"
  },
  {
    "question_id": "wikisql_c8bc677481_003",
    "table_id": "wikisql_c8bc677481",
    "question_type": "value",
    "question": "USL PDL में खेलते हुए जिस पहले साल टीम ने रेगुलर सीज़न में पहला स्थान हासिल किया, उसमें टीम का ओपन कप का नतीजा क्या था?",
    "answer": [
      [
        "Did not qualify"
      ]
    ],
    "evidence_cells": [
      "A5",
      "C5",
      "D5",
      "F5",
      "A8",
      "C8",
      "D8",
      "A9",
      "C9",
      "D9"
    ],
    "reasoning_category": "Multi-Hop Reasoning"
  },
  {
    "question_id": "wikisql_c8bc677481_004",
    "table_id": "wikisql_c8bc677481",
    "question_type": "open_ended_reasoning",
    "question": "1997 से 2000 तक USISL/USL A-League में रहते हुए टीम के ओपन कप प्रदर्शन की प्रगति का वर्णन करें।",
    "answer": [
      [
        "इस अवधि के दौरान टीम का ओपन कप प्रदर्शन असंगत था। 1997 में क्वालीफाई नहीं करने के बाद, उन्होंने 1998 में 3rd Round में पहुंचकर इस युग का अपना सर्वश्रेष्ठ परिणाम प्राप्त किया। इसके बाद 1999 में 2nd Round तक गिरावट आई, और वे 2000 में फिर से क्वालीफाई करने में विफल रहे, जिसमें कोई स्थायी प्रवृत्ति नहीं दिखी।"
      ]
    ],
    "evidence_cells": [
      "A1",
      "F1",
      "A2",
      "F2",
      "A3",
      "F3",
      "A4",
      "F4"
    ],
    "reasoning_category": "Temporal Reasoning"
  },
  {
    "question_id": "wikisql_c8bc677481_005",
    "table_id": "wikisql_c8bc677481",
    "question_type": "value",
    "question": "'USL PDL' लीग में खेले गए और प्लेऑफ़ में 'नेशनल सेमीफ़ाइनल्स' तक पहुँचने वाले वर्षों की सूची बनाएँ।",
    "answer": [
      [
        "2003"
      ],
      [
        "2005"
      ],
      [
        "2006"
      ]
    ],
    "evidence_cells": [
      "A7",
      "C7",
      "E7",
      "A9",
      "C9",
      "E9",
      "A10",
      "C10",
      "E10"
    ],
    "reasoning_category": "Conditional Reasoning"
  },
  {
    "question_id": "wikisql_c8bc677481_006",
    "table_id": "wikisql_c8bc677481",
    "question_type": "value",
    "question": "सूचीबद्ध कुल सीज़न में से कितने प्रतिशत सीज़न प्लेऑफ़ के लिए योग्य रहे?",
    "answer": [
      [
        "40%"
      ]
    ],
    "evidence_cells": [
      "E1",
      "E2",
      "E3",
      "E4",
      "E5",
      "E6",
      "E7",
      "E8",
      "E9",
      "E10",
      "E11",
      "E12",
      "E13",
      "E14",
      "E15"
    ],
    "reasoning_category": "Proportional/Ratio Analysis"
  },
  {
    "question_id": "wikisql_c8bc677481_007",
    "table_id": "wikisql_c8bc677481",
    "question_type": "value",
    "question": "यदि 'सफल' प्लेऑफ़ रन की परिभाषा को 'कॉन्फ़्रेंस फ़ाइनल' या उससे बेहतर तक पहुँचने के लिए बदल दिया जाए, तो टीम के कितने सफल रन होंगे यदि उनके 1999 के 'कॉन्फ़्रेंस क्वार्टरफ़ाइनल' के परिणाम को 'कॉन्फ़्रेंस फ़ाइनल' में अपग्रेड कर दिया जाए?",
    "answer": [
      [
        "5"
      ]
    ],
    "evidence_cells": [
      "E3",
      "E7",
      "E8",
      "E9",
      "E10"
    ],
    "reasoning_category": "Hypothetical Reasoning"
  },
  {
    "question_id": "wikisql_c8bc677481_008",
    "table_id": "wikisql_c8bc677481",
    "question_type": "open_ended_reasoning",
    "question": "क्या टीम के डिवीज़न स्तर और प्लेऑफ़ के लिए क्वालीफाई करने की उनकी क्षमता के बीच कोई स्पष्ट संबंध है?",
    "answer": [
      [
        "हाँ, डेटा बताता है कि टीम डिवीज़न 4 में खेलते समय प्लेऑफ़ के लिए क्वालीफाई करने की अधिक संभावना रखती थी। उन्होंने डिवीज़न 4 में अपने 45.5% सीज़न (11 में से 5) में क्वालीफाई किया, जबकि डिवीज़न 2 में केवल 25% सीज़न (4 में से 1) में क्वालीफाई किया, जिससे पता चलता है कि वे निचले डिवीज़न में अपने साथियों के खिलाफ अधिक प्रतिस्पर्धी थे।"
      ]
    ],
    "evidence_cells": [
      "B1",
      "B2",
      "B3",
      "B4",
      "E1",
      "E2",
      "E3",
      "E4",
      "B5",
      "B6",
      "B7",
      "B8",
      "B9",
      "B10",
      "B11",
      "B12",
      "B13",
      "B14",
      "B15",
      "E5",
      "E6",
      "E7",
      "E8",
      "E9",
      "E10",
      "E11",
      "E12",
      "E13",
      "E14",
      "E15"
    ],
    "reasoning_category": "Correlation Inference"
  },
  {
    "question_id": "wikisql_c8bc677481_009",
    "table_id": "wikisql_c8bc677481",
    "question_type": "value",
    "question": "'प्लेऑफ़' या 'ओपन कप' में से किस कॉलम में कम अनूठी परिणाम श्रेणियां हैं?",
    "answer": [
      [
        "Open Cup"
      ]
    ],
    "evidence_cells": [
      "E1",
      "E2",
      "E3",
      "E4",
      "E5",
      "E6",
      "E7",
      "E8",
      "E9",
      "E10",
      "E11",
      "E12",
      "E13",
      "E14",
      "E15",
      "F1",
      "F2",
      "F3",
      "F4",
      "F5",
      "F6",
      "F7",
      "F8",
      "F9",
      "F10",
      "F11",
      "F12",
      "F13",
      "F14",
      "F15"
    ],
    "reasoning_category": "Structural/Metadata Reasoning"
  },
  {
    "question_id": "wikisql_c8bc677481_010",
    "table_id": "wikisql_c8bc677481",
    "question_type": "value",
    "question": "USL PDL (2001-2011) के दौरान टीम के नियमित सीज़न प्रदर्शन में किस वर्ष में सबसे महत्वपूर्ण नकारात्मक आउटलायर का प्रतिनिधित्व करता है?",
    "answer": [
      [
        "2007"
      ]
    ],
    "evidence_cells": [
      "A5",
      "D5",
      "A6",
      "D6",
      "A7",
      "D7",
      "A8",
      "D8",
      "A9",
      "D9",
      "A10",
      "D10",
      "A11",
      "D11"
    ],
    "reasoning_category": "Outlier Detection"
  },
  {
    "question_id": "wikisql_c8bc677481_011",
    "table_id": "wikisql_c8bc677481",
    "question_type": "value",
    "question": "किस वर्ष में समग्र रूप से सर्वश्रेष्ठ प्लेऑफ़ प्रदर्शन था?",
    "answer": [
      [
        "2003"
      ]
    ],
    "evidence_cells": [
      "A7",
      "E7"
    ],
    "reasoning_category": "Comparative Reasoning"
  }
]