[
  {
    "question_id": "arxiv_77d21be6b3_001",
    "table_id": "arxiv_77d21be6b3",
    "question_type": "value",
    "question": "'Parametric (PM)' 범주에 속하는 모델은 몇 개입니까?",
    "answer": [
      [
        "6"
      ]
    ],
    "evidence_cells": [
      "B3",
      "B4",
      "B5",
      "B6",
      "B7",
      "B8"
    ],
    "reasoning_category": "Numerical Aggregation"
  },
  {
    "question_id": "arxiv_77d21be6b3_002",
    "table_id": "arxiv_77d21be6b3",
    "question_type": "value",
    "question": "표에서 가장 많은 모델이 나열된 모델 범주는 무엇입니까?",
    "answer": [
      [
        "Parametric (PM)"
      ],
      [
        "Neural network (NN)"
      ]
    ],
    "evidence_cells": [
      "B1",
      "B2",
      "B3",
      "B4",
      "B5",
      "B6",
      "B7",
      "B8",
      "B9",
      "B10",
      "B11",
      "B12",
      "B13",
      "B14"
    ],
    "reasoning_category": "Comparative Reasoning"
  },
  {
    "question_id": "arxiv_77d21be6b3_003",
    "table_id": "arxiv_77d21be6b3",
    "question_type": "value",
    "question": "'return of yields'를 명시적으로 언급하는 모든 모델의 이름을 나열하십시오.",
    "answer": [
      [
        "AR_RET"
      ],
      [
        "GARCH_RET"
      ],
      [
        "GARCHt_RET"
      ]
    ],
    "evidence_cells": [
      "C4",
      "D4",
      "C6",
      "D6",
      "C7",
      "D7"
    ],
    "reasoning_category": "Conditional Reasoning"
  },
  {
    "question_id": "arxiv_77d21be6b3_004",
    "table_id": "arxiv_77d21be6b3",
    "question_type": "value",
    "question": "'Historical simulation (HS)' 범주에서 필터링을 포함하는 유일한 모델의 전체 설명(Note)은 무엇입니까?",
    "answer": [
      [
        "Filtered historical simulation (EWMA)"
      ]
    ],
    "evidence_cells": [
      "B1",
      "D1",
      "B2",
      "D2"
    ],
    "reasoning_category": "Multi-Hop Reasoning"
  },
  {
    "question_id": "arxiv_77d21be6b3_005",
    "table_id": "arxiv_77d21be6b3",
    "question_type": "value",
    "question": "'Neural network (NN)'로 분류된 전체 모델 중 몇 퍼센트입니까?",
    "answer": [
      [
        "42.86%"
      ]
    ],
    "evidence_cells": [
      "A1",
      "A2",
      "A3",
      "A4",
      "A5",
      "A6",
      "A7",
      "A8",
      "A9",
      "A10",
      "A11",
      "A12",
      "A13",
      "A14",
      "B9",
      "B10",
      "B11",
      "B12",
      "B13",
      "B14"
    ],
    "reasoning_category": "Proportional/Ratio Analysis"
  },
  {
    "question_id": "arxiv_77d21be6b3_006",
    "table_id": "arxiv_77d21be6b3",
    "question_type": "value",
    "question": "표에서 가장 적게 나타나 빈도 면에서 특이치에 해당하는 모델 카테고리는 무엇입니까?",
    "answer": [
      [
        "Historical simulation (HS)"
      ]
    ],
    "evidence_cells": [
      "B1",
      "B2",
      "B3",
      "B4",
      "B5",
      "B6",
      "B7",
      "B8",
      "B9",
      "B10",
      "B11",
      "B12",
      "B13",
      "B14"
    ],
    "reasoning_category": "Outlier Detection"
  },
  {
    "question_id": "arxiv_77d21be6b3_007",
    "table_id": "arxiv_77d21be6b3",
    "question_type": "value",
    "question": "'수익률 반환'에서 작동하는 모든 모델을 '반환 기반'이라는 새 범주로 옮긴다면, 이 새 범주에는 몇 개의 모델이 포함됩니까?",
    "answer": [
      [
        "3"
      ]
    ],
    "evidence_cells": [
      "D4",
      "D6",
      "D7"
    ],
    "reasoning_category": "Hypothetical Reasoning"
  },
  {
    "question_id": "arxiv_77d21be6b3_008",
    "table_id": "arxiv_77d21be6b3",
    "question_type": "open_ended_reasoning",
    "question": "'Parametric (PM)' 범주 내에서 'return of yields'에 대해 작동하는 모델과 'yields'에 대해 작동하는 모델을 구별하기 위해 'Model Name'에 사용되는 공통 접미사는 무엇입니까?",
    "answer": [
      [
        "공통 접미사는 '_RET'입니다. 이는 'AR'(yields 모델)과 'AR_RET'(return of yields 모델)을 비교하거나 'GARCH'와 'GARCH_RET'를 비교하여 확인할 수 있습니다."
      ]
    ],
    "evidence_cells": [
      "C3",
      "D3",
      "C4",
      "D4",
      "C5",
      "D5",
      "C6",
      "D6"
    ],
    "reasoning_category": "Structural/Metadata Reasoning"
  },
  {
    "question_id": "arxiv_77d21be6b3_009",
    "table_id": "arxiv_77d21be6b3",
    "question_type": "open_ended_reasoning",
    "question": "'CGAN-FC'와 'CGAN-LSTM'의 데이터에 따르면, 'Neural network (NN)' 범주 내에서 모델의 이름과 그 기반 아키텍처 간에 어떤 관계를 추론할 수 있습니까?",
    "answer": [
      [
        "모델 이름의 접미사(예: '-FC', '-LSTM')가 'Note'에 상세히 설명된 네트워크 계층 유형('fully connected layers', 'LSTM layers')을 명시적으로 설명하는 직접적인 관계를 추론할 수 있습니다. 이는 모델 아키텍처를 빠르게 식별하기 위한 체계적인 명명 규칙을 시사합니다."
      ]
    ],
    "evidence_cells": [
      "C9",
      "D9",
      "C10",
      "D10"
    ],
    "reasoning_category": "Correlation Inference"
  },
  {
    "question_id": "arxiv_77d21be6b3_010",
    "table_id": "arxiv_77d21be6b3",
    "question_type": "open_ended_reasoning",
    "question": "'모수적(PM)' 범주와 '신경망(NN)' 범주 내 모델들의 내부 다양성을 비교해 주십시오. 설명에 따르면 어떤 범주가 더 넓은 범위의 뚜렷한 모델링 접근 방식을 가지고 있는 것으로 보입니까?",
    "answer": [
      [
        "'신경망(NN)' 범주가 더 큰 내부 다양성을 보입니다. '모수적(PM)' 모델들은 주로 입력 데이터(수익률 또는 수익률의 수익률)나 오류 분포에 따라 AR 및 GARCH와 같은 기존 통계 프레임워크의 변형인 반면, '신경망(NN)' 범주는 근본적으로 다른 아키텍처를 포함합니다. 다양한 생성적 적대 신경망(CGAN, CWGAN), 확산 모델, 그리고 변이형 오토인코더(VAE)를 포함하며, 이는 더 넓은 범위의 뚜렷한 머신러닝 기법들을 나타냅니다."
      ]
    ],
    "evidence_cells": [
      "B3",
      "D3",
      "B4",
      "D4",
      "B5",
      "D5",
      "B6",
      "D6",
      "B7",
      "D7",
      "B8",
      "D8",
      "B9",
      "D9",
      "B10",
      "D10",
      "B11",
      "D11",
      "B12",
      "D12",
      "B13",
      "D13",
      "B14",
      "D14"
    ],
    "reasoning_category": "Comparative Reasoning"
  },
  {
    "question_id": "arxiv_77d21be6b3_011",
    "table_id": "arxiv_77d21be6b3",
    "question_type": "open_ended_reasoning",
    "question": "PHS는 무엇을 의미하며 어떤 종류의 모델입니까?",
    "answer": [
      [
        "PHS는 Plain Historical Simulation을 의미하며, Historical simulation (HS) 모델입니다."
      ]
    ],
    "evidence_cells": [
      "B1",
      "C1",
      "D1"
    ],
    "reasoning_category": "Structural/Metadata Reasoning"
  }
]